gtirb_test_helpers/__init__.py
gtirb_test_helpers/helpers.py
gtirb_test_helpers/py.typed
gtirb_test_helpers/version.py
gtirb_test_helpers-2.0.0.dist-info/LICENSE.txt
gtirb_test_helpers-2.0.0.dist-info/METADATA
gtirb_test_helpers-2.0.0.dist-info/WHEEL
gtirb_test_helpers-2.0.0.dist-info/top_level.txt
gtirb_test_helpers-2.0.0.dist-info/RECORD
